Workbook

Sheet Overview
A1: Loop — Implementation Tracker
A2: Companion to /loop_implementation/. Update weekly.
A4: Owner | B4: CTO
A5: Last updated | B5: =TODAY() -> 46141
A6: Sprint length | B6: 2 weeks (Sprint 0 is 6w bootstrap)
A7: Working days / sprint | B7: 10
A9: Quick links
A10: Architecture | B10: loop_implementation/architecture/ARCHITECTURE.md
A11: Data model | B11: loop_implementation/data/SCHEMA.md
A12: API spec | B12: loop_implementation/api/openapi.yaml
A13: ADRs | B13: loop_implementation/adrs/README.md
A14: UX/UI | B14: loop_implementation/ux/UX_DESIGN.md
A15: Engineering handbook | B15: loop_implementation/engineering/HANDBOOK.md
A16: Security | B16: loop_implementation/engineering/SECURITY.md
A17: Testing | B17: loop_implementation/engineering/TESTING.md
A18: Sprint 0 plan | B18: loop_implementation/tracker/SPRINT_0.md
A19: Master spec | B19: botpress_competitor_spec.md
A22: Status legend
A23: Done
A24: In progress
A25: Blocked
A26: At risk
A27: Not started

Sheet Epics
A1: Epics
A2: High-level workstreams. Each epic owns multiple stories on the Stories sheet.
A4: ID | B4: Epic | C4: Owner | D4: Target milestone | E4: Status | F4: Stories total | G4: Stories done | H4: % complete | I4: Notes
A5: E1 | B5: Agent runtime core | C5: Eng #1 | D5: MVP M6 | E5: In progress | F5: =COUNTIF(Stories!E:E,"E1") -> 4 | G5: =COUNTIFS(Stories!E:E,"E1",Stories!H:H,"Done") -> 0 | H5: =IF(F5=0,0,G5/F5) -> 0 | I5: Hot path: TurnExecutor, streaming, budgets, idempotency
A6: E2 | B6: LLM Gateway | C6: Eng #1 | D6: MVP M6 | E6: Not started | F6: =COUNTIF(Stories!E:E,"E2") -> 2 | G6: =COUNTIFS(Stories!E:E,"E2",Stories!H:H,"Done") -> 0 | H6: =IF(F6=0,0,G6/F6) -> 0 | I6: Multi-provider, semantic cache, cost accounting
A7: E3 | B7: MCP / Tool layer | C7: Eng #1 | D7: MVP M6 | E7: Not started | F7: =COUNTIF(Stories!E:E,"E3") -> 2 | G7: =COUNTIFS(Stories!E:E,"E3",Stories!H:H,"Done") -> 0 | H7: =IF(F7=0,0,G7/F7) -> 0 | I7: Auto-MCP, Firecracker sandboxes, allow-lists
A8: E4 | B8: Memory tiers | C8: Eng #1 | D8: MVP M6 | E8: Not started | F8: =COUNTIF(Stories!E:E,"E4") -> 2 | G8: =COUNTIFS(Stories!E:E,"E4",Stories!H:H,"Done") -> 0 | H8: =IF(F8=0,0,G8/F8) -> 0 | I8: User/session/scratch + episodic at M7
A9: E5 | B9: KB / RAG engine | C9: Eng #1 | D9: MVP M6 | E9: Not started | F9: =COUNTIF(Stories!E:E,"E5") -> 1 | G9: =COUNTIFS(Stories!E:E,"E5",Stories!H:H,"Done") -> 0 | H9: =IF(F9=0,0,G9/F9) -> 0 | I9: PDF/web/Notion + hybrid retrieval + vision
A10: E6 | B10: Channel adapters | C10: Eng #7 | D10: Rolling | E10: Not started | F10: =COUNTIF(Stories!E:E,"E6") -> 5 | G10: =COUNTIFS(Stories!E:E,"E6",Stories!H:H,"Done") -> 0 | H10: =IF(F10=0,0,G10/F10) -> 0 | I10: Web, Slack, WhatsApp, SMS first
A11: E7 | B11: Voice subsystem | C11: Eng #3 | D11: MVP M6 | E11: Not started | F11: =COUNTIF(Stories!E:E,"E7") -> 4 | G11: =COUNTIFS(Stories!E:E,"E7",Stories!H:H,"Done") -> 0 | H11: =IF(F11=0,0,G11/F11) -> 0 | I11: WebRTC + STT + TTS + barge-in. Sub-700ms p50
A12: E8 | B12: Eval harness | C12: Eng #4 | D12: MVP M6 | E12: Not started | F12: =COUNTIF(Stories!E:E,"E8") -> 4 | G12: =COUNTIFS(Stories!E:E,"E8",Stories!H:H,"Done") -> 0 | H12: =IF(F12=0,0,G12/F12) -> 0 | I12: 8 scorers, replay, registry
A13: E9 | B13: Observability backend | C13: Eng #4 | D13: MVP M6 | E13: Not started | F13: =COUNTIF(Stories!E:E,"E9") -> 1 | G13: =COUNTIFS(Stories!E:E,"E9",Stories!H:H,"Done") -> 0 | H13: =IF(F13=0,0,G13/F13) -> 0 | I13: OTel + ClickHouse + Studio dashboards
A14: E10 | B14: Studio (UI) | C14: Eng #5 | D14: MVP M6 | E14: Not started | F14: =COUNTIF(Stories!E:E,"E10") -> 5 | G14: =COUNTIFS(Stories!E:E,"E10",Stories!H:H,"Done") -> 0 | H14: =IF(F14=0,0,G14/F14) -> 0 | I14: Conversations, traces, replay, costs
A15: E11 | B15: CLI & SDKs | C15: Eng #1+5 | D15: MVP M6 | E15: Not started | F15: =COUNTIF(Stories!E:E,"E11") -> 1 | G15: =COUNTIFS(Stories!E:E,"E11",Stories!H:H,"Done") -> 0 | H15: =IF(F15=0,0,G15/F15) -> 0 | I15: Python core, Go CLI; TS gen later
A16: E12 | B16: Cloud control plane | C16: Eng #2 | D16: MVP M6 | E16: Not started | F16: =COUNTIF(Stories!E:E,"E12") -> 6 | G16: =COUNTIFS(Stories!E:E,"E12",Stories!H:H,"Done") -> 0 | H16: =IF(F16=0,0,G16/F16) -> 0 | I16: Auth, billing, deploy, multi-tenant
A17: E13 | B17: Self-host (docker-compose + Helm) | C17: Eng #2 | D17: M7 | E17: Not started | F17: =COUNTIF(Stories!E:E,"E13") -> 2 | G17: =COUNTIFS(Stories!E:E,"E13",Stories!H:H,"Done") -> 0 | H17: =IF(F17=0,0,G17/F17) -> 0 | I17: Compose at MVP, Helm at M7
A18: E14 | B18: Multi-agent orchestration | C18: Eng #1 | D18: M9 | E18: Not started | F18: =COUNTIF(Stories!E:E,"E14") -> 2 | G18: =COUNTIFS(Stories!E:E,"E14",Stories!H:H,"Done") -> 0 | H18: =IF(F18=0,0,G18/F18) -> 0 | I18: Supervisor, Pipeline, Parallel, AgentGraph
A19: E15 | B19: HITL / Operator inbox | C19: Eng #5 | D19: M7 | E19: Not started | F19: =COUNTIF(Stories!E:E,"E15") -> 2 | G19: =COUNTIFS(Stories!E:E,"E15",Stories!H:H,"Done") -> 0 | H19: =IF(F19=0,0,G19/F19) -> 0 | I19: Takeover, shared inbox, CRM connectors
A20: E16 | B20: Security & compliance (SOC2 Type 1) | C20: Sec eng | D20: M12 | E20: Not started | F20: =COUNTIF(Stories!E:E,"E16") -> 1 | G20: =COUNTIFS(Stories!E:E,"E16",Stories!H:H,"Done") -> 0 | H20: =IF(F20=0,0,G20/F20) -> 0 | I20: Vanta, audit log, RLS, KMS
A21: E17 | B21: Docs site & DevRel | C21: Eng #6 | D21: Rolling | E21: Not started | F21: =COUNTIF(Stories!E:E,"E17") -> 2 | G21: =COUNTIFS(Stories!E:E,"E17",Stories!H:H,"Done") -> 0 | H21: =IF(F21=0,0,G21/F21) -> 0 | I21: Quickstart, API ref, examples
A22: E18 | B22: MCP marketplace | C22: Eng #6 | D22: M6 | E22: Not started | F22: =COUNTIF(Stories!E:E,"E18") -> 1 | G22: =COUNTIFS(Stories!E:E,"E18",Stories!H:H,"Done") -> 0 | H22: =IF(F22=0,0,G22/F22) -> 0 | I22: 25 servers at MVP, 200 by M12
A23: E19 | B23: Pricing & billing | C23: Eng #2 | D23: M6 | E23: Not started | F23: =COUNTIF(Stories!E:E,"E19") -> 1 | G23: =COUNTIFS(Stories!E:E,"E19",Stories!H:H,"Done") -> 0 | H23: =IF(F23=0,0,G23/F23) -> 0 | I23: Stripe + 3-meter + cap rules
A24: E20 | B24: Enterprise (SSO, audit UI, on-prem parity) | C24: Eng #2+sec | D24: M12 | E24: Not started | F24: =COUNTIF(Stories!E:E,"E20") -> 1 | G24: =COUNTIFS(Stories!E:E,"E20",Stories!H:H,"Done") -> 0 | H24: =IF(F24=0,0,G24/F24) -> 0 | I24: SAML, residency, BYOK

Sheet Stories
A1: Stories
A2: Sprint-sized work items. Map back to an Epic via the Epic column.
A4: ID | B4: Story | C4: Owner | D4: Sprint | E4: Epic | F4: Estimate (pts) | G4: Priority | H4: Status | I4: Notes
A5: S001 | B5: Repo init, CI skeleton, branch protection, CODEOWNERS | C5: CTO | D5: S0 | E5: E12 | F5: 3 | G5: P0 | H5: Not started | I5: Week 1
A6: S002 | B6: Cloud accounts (chosen launch cloud — see CLOUD_PORTABILITY.md), Auth0 dev tenant, Stripe test, Sentry, Linear, PagerDuty | C6: CTO | D6: S0 | E6: E12 | F6: 5 | G6: P0 | H6: Not started | I6: Week 1
A7: S003 | B7: docker-compose: Postgres, Redis, Qdrant, NATS, MinIO, ClickHouse, OTel | C7: Eng #2 | D7: S0 | E7: E13 | F7: 5 | G7: P0 | H7: Not started | I7: Week 1
A8: S004 | B8: Runtime package skeleton; AgentEvent/AgentResponse/Turn types | C8: Eng #1 | D8: S0 | E8: E1 | F8: 5 | G8: P0 | H8: Not started | I8: Week 1
A9: S005 | B9: Studio Next.js skeleton + shadcn/ui + Tailwind | C9: Eng #5 | D9: S0 | E9: E10 | F9: 3 | G9: P0 | H9: Not started | I9: Week 1
A10: S006 | B10: Postgres migrations: control plane + data plane core tables | C10: Eng #2 | D10: S0 | E10: E12 | F10: 5 | G10: P0 | H10: Not started | I10: Week 2
A11: S007 | B11: LLM Gateway client: streaming OpenAI + Anthropic | C11: Eng #1 | D11: S0 | E11: E2 | F11: 8 | G11: P0 | H11: Not started | I11: Week 2
A12: S008 | B12: TurnExecutor reasoning loop v0 (no tools yet) | C12: Eng #1 | D12: S0 | E12: E1 | F12: 8 | G12: P0 | H12: Not started | I12: Week 2
A13: S009 | B13: OTel collector wired; first span exported to ClickHouse | C13: Eng #4 | D13: S0 | E13: E9 | F13: 5 | G13: P0 | H13: Not started | I13: Week 2
A14: S010 | B14: Studio agents-list page (read from cp-api) | C14: Eng #5 | D14: S0 | E14: E10 | F14: 3 | G14: P1 | H14: Not started | I14: Week 2
A15: S011 | B15: MCP client; auto-MCP decorator for Python functions | C15: Eng #1 | D15: S0 | E15: E3 | F15: 8 | G15: P0 | H15: Not started | I15: Week 3
A16: S012 | B16: Multi-iteration reasoning loop with parallel tool dispatch | C16: Eng #1 | D16: S0 | E16: E1 | F16: 5 | G16: P0 | H16: Not started | I16: Week 3
... A54: S050 | B54: Enterprise GA: SSO/SAML, audit log UI, on-prem parity | C54: Eng #2 | D54: S1 | E54: E20 | F54: 13 | G54: P0 | H54: Not started | I54: M12

Sheet Sprints
A1: Sprint plan
A2: Sprint 0 = 6-week bootstrap. Subsequent sprints are 2 weeks.
A4: Sprint | B4: Window | C4: Theme | D4: Goal | E4: Stories | F4: Total points | G4: Status
A5: S0 | B5: Wk 1–6 | C5: Bootstrap | D5: Local stack + first turn + first deploy + 3 design partners onboarded | E5: S001-S034 | F5: =SUMIFS(Stories!F:F,Stories!D:D,A5) -> 196 | G5: Not started
A6: S1 | B6: Wk 7–8 | C6: Episodic memory + Helm | D6: Episodic memory; helm chart; email + telegram; multi-agent v0 | E6: S035-S038 | F6: =SUMIFS(Stories!F:F,Stories!D:D,A6) -> 165 | G6: Not started
A7: S2 | B7: Wk 9–10 | C7: TS SDK + Discord/Teams + replay | D7: TS SDK GA; Discord + Teams; replay debugging in Studio | E7: S039-S041 | F7: =SUMIFS(Stories!F:F,Stories!D:D,A7) -> 0 | G7: Not started
A8: S3 | B8: Wk 11–12 | C8: Multi-agent GA + eval registry + Series A | D8: Parallel + AgentGraph; public eval registry; Series A narrative | E8: S042-S044 | F8: =SUMIFS(Stories!F:F,Stories!D:D,A8) -> 0 | G8: Not started
A9: S4 | B9: Wk 13–14 | C9: EU region + SOC2 kickoff | D9: Deploy `eu-west` (cloud-agnostic); Vanta; Salesforce + Zendesk MCP | E9: S045-S047 | F9: =SUMIFS(Stories!F:F,Stories!D:D,A9) -> 0 | G9: Not started
A10: S5 | B10: Wk 15–16 | C10: Voice latency + phone provisioning | D10: Voice ≤700ms; phone number provisioning | E10: S048-S049 | F10: =SUMIFS(Stories!F:F,Stories!D:D,A10) -> 0 | G10: Not started
A11: S6 | B11: Wk 17–18 | C11: Enterprise GA | D11: SSO/SAML, audit UI, on-prem parity, SOC2 Type 1 done | E11: S050 | F11: =SUMIFS(Stories!F:F,Stories!D:D,A11) -> 0 | G11: Not started

Sheet Hiring
A1: Hiring plan
A2: First 8 engineers. Onboarding sequence in HANDBOOK.md §11.
A4: # | B4: Role | C4: Why first | D4: Start month | E4: Stage | F4: Owner | G4: Notes
A5: 1 | B5: Founding engineer — Runtime (Python core) | C5: Owns the agent loop. Senior, opinionated. | D5: M0 | E5: Searching | F5: CTO | G5: Bar: shipped a high-throughput Python service before
A6: 2 | B6: Founding engineer — Infra / Platform | C6: Postgres, Redis, NATS, k8s, Terraform. Builds data plane. | D6: M0 | E6: Searching | F6: CTO | G6: Bar: production k8s, observability
A7: 3 | B7: Founding engineer — Voice / Real-time | C7: WebRTC, STT/TTS, latency. The voice moat. | D7: M0 | E7: Pipeline | F7: CTO | G7: Bar: ≤500ms voice in prod
A8: 4 | B8: Founding engineer — Observability + Eval harness | C8: ClickHouse, OTel, eval scorers. The other moat. | D8: M1 | E8: Pipeline | F8: CTO | G8: Bar: scaled tracing/eval system before
A9: 5 | B9: Founding engineer — Full-stack / Studio | C9: Next.js, React, tRPC. Debugger UI. | D9: M1 | E9: Pipeline | F9: CTO | G9: Bar: shipped a polished web app to GA
A10: 6 | B10: DevRel / Docs engineer | C10: Examples, blog, docs, MCP server contributions. OSS adoption. | D10: M3 | E10: Pipeline | F10: CEO | G10: Critical for community velocity
A11: 7 | B11: Senior engineer — Channel integrations | C11: WhatsApp, Slack, Teams, email. Compounding work. | D11: M3 | E11: Pipeline | F11: CTO | G11: Bar: 3+ external API integrations
A12: 8 | B12: Security / Compliance engineer | C12: SOC2, HIPAA-readiness, audit logs, secrets. Unlocks enterprise. | D12: M5 | E12: Searching | F12: CTO | G12: Bar: led SOC2 effort end-to-end

Sheet Risks
A1: Risks register
A2: Reviewed weekly. Severity × Likelihood = priority.
A4: ID | B4: Risk | C4: Likelihood | D4: Severity | E4: Owner | F4: Mitigation | G4: Status
A5: R1 | B5: Frontier-lab SDKs (OpenAI Agents, Claude Agent) eat the category | C5: Med | D5: High | E5: CEO | F5: Be the agnostic Switzerland. Run on every provider. Own observability + evals + voice as differentiators. | G5: Watching
A6: R2 | B6: MCP standard fragments (OpenAI/Google compete) | C6: Low | D6: Med | E6: Eng #1 | F6: MCP-first but adapter-flexible; can speak OpenAI tool format too. | G6: Watching
A7: R3 | B7: Voice latency target (≤700ms p50) misses | C7: Med | D7: High | E7: Eng #3 | F7: Schedule slip is acceptable; ship voice at M7 instead of MVP. Edge POPs + warm pool. | G7: Watching
A8: R4 | B8: Hire #1 (runtime) takes >60 days to fill | C8: Med | D8: High | E8: CTO | F8: CTO writes first-draft TurnExecutor; new hire inherits. Multiple parallel candidates. | G8: Active
A9: R5 | B9: Botpress closes the gap (voice + MCP + true OSS in 12mo) | C9: Low | D9: Med | E9: CEO | F9: Architecture mid-pivot makes this unlikely. We move faster on each axis. | G9: Watching
A10: R6 | B10: Runtime engineering complexity (async + streaming + sandboxes) | C10: Med | D10: High | E10: Eng #1 | F10: Hire bar #1 must be exceptional. Sprint 0 establishes a working baseline. | G10: Active
A11: R7 | B11: Compliance burden (SOC2, HIPAA) blocks enterprise revenue | C11: Med | D11: High | E11: Sec eng | F11: Vanta day 1. Hire sec eng by M5. SOC2 Type 1 by M12. | G11: Watching
A12: R8 | B12: OSS license arbitrage (hyperscaler offers managed Loop) | C12: Low | D12: Med | E12: CEO | F12: Apache 2.0 accepts the risk; brand + control plane + network effects are the moat. | G12: Watching
A13: R9 | B13: Eval harness over-promises; teams don't adopt | C13: Med | D13: Med | E13: Eng #4 | F13: `loop eval init` scaffolds from production replay automatically. Public registry seeds value. | G13: Watching
A14: R10 | B14: Cost overruns on infra (LLM, ClickHouse, voice POPs) | C14: Med | D14: Med | E14: CTO | F14: Budget caps + monthly review. Negotiate annual commits with providers post-Series A. | G14: Watching
A15: R11 | B15: Channel provider terms change (Meta WhatsApp policies) | C15: High | D15: Low | E15: Eng #7 | F15: Multi-BSP support; document fallback path; surface channel cost on invoice. | G15: Watching
A16: R12 | B16: Studio scope creep (users want a flow editor) | C16: Med | D16: Low | E16: Eng #5 | F16: Politely decline. Code-first is the wedge. Optional read-only DAG view at M9. | G16: Active

Sheet Roadmap
A1: 12-month roadmap
A2: Mirrors the master spec. Months map to sprints S0–S6+.
A4: Month | B4: Milestone | C4: Key deliverables | D4: Status
A5: M0 | B5: Hire + scope | C5: Hire engineers 1–4; tech-stack lock-in; runtime + SDK started | D5: Not started
A6: M1 | B6: Runtime alpha | C6: Python SDK skeleton; LLM gateway w/ OpenAI + Anthropic; Slack channel | D6: Not started
A7: M2 | B7: Tools + KB | C7: Tool/MCP layer; auto-MCP; KB ingestion v0; web widget | D7: Not started
A8: M3 | B8: Eval + cloud | C8: Eval harness v0 (6 scorers); CLI v0; cloud control plane (auth, deploy) | D8: Not started
A9: M4 | B9: Closed alpha | C9: 10 design partners; WhatsApp; Studio v0 (conversations + traces) | D9: Not started
A10: M5 | B10: Voice MVP | C10: Voice channel MVP; memory tiers; cost dashboard | D10: Not started
A11: M6 | B11: Public beta | C11: OSS the runtime (Apache 2.0); Hub v0; free hobby tier; PUBLIC BETA | D11: Not started
A12: M7 | B12: Episodic + helm | C12: Episodic memory; Helm chart; email + Telegram; multi-agent primitives v0 | D12: Not started
A13: M8 | B13: TS SDK + replay | C13: TS SDK GA; Discord + Teams; replay/time-travel debugging | D13: Not started
A14: M9 | B14: Multi-agent GA | C14: Multi-agent GA (Graph, Parallel, Blackboard); public eval registry; Series A | D14: Not started
A15: M10 | B15: EU + SOC2 | C15: EU region (`eu-west`, cloud-agnostic); SOC2 Type 1 kickoff; Salesforce + Zendesk MCP | D15: Not started
... A17: M12 | B17: Enterprise GA | C17: SSO/SAML, audit logs, on-prem parity, SOC2 Type 1 done; ENTERPRISE GA | D17: Not started

Sheet Budgets
A1: Budgets & metrics
A2: Working numbers — refine with finance once seed closes.
A4: Performance budgets (hard)
A5: Metric | B5: Target | C5: Owner
A6: Voice latency p50 (end-to-end) | B6: ≤ 700 ms | C6: Eng #3
A7: Chat first-token p50 | B7: ≤ 600 ms | C7: Eng #1
A8: Chat p99 | B8: ≤ 2000 ms | C8: Eng #1
A9: API availability (Pro/Team) | B9: 99.9% | C9: Eng #2
A10: API availability (Enterprise) | B10: 99.95% | C10: Eng #2
A11: Trace ingestion lag | B11: ≤ 5 s | C11: Eng #4
A12: Cold start (warm pool) | B12: 0 (not user-visible) | C12: Eng #2
A13: Deploy time (push → live) | B13: ≤ 60 s | C13: Eng #2
A14: Eval suite of 100 cases | B14: ≤ 90 s | C14: Eng #4
A15: Concurrent conversations / pod | B15: 100 | C15: Eng #1
A18: Unit-economics targets (steady state)
A19: Metric | B19: Target | C19: Notes
A20: Gross margin | B20: 75% | C20: LLM ~95% on 5%, compute ~70%, storage ~85%
A21: LTV : CAC | B21: ≥ 3 : 1 by month 18 | C21: Bottom-up PLG with sales-led at the top
A22: ARR per FTE (by M24) | B22: $300K | C22: Industry P75 for OSS/PLG infra
A23: LLM token markup | B23: 5%, fully disclosed | C23: Trust commitment
A24: Hard-cap behavior | B24: Graceful degrade, never drop | C24: Trust commitment
